codescribe/__init__.py
codescribe/formatter.py
codescribe/github_api.py
codescribe-1.0.4.dist-info/METADATA
codescribe-1.0.4.dist-info/WHEEL
codescribe-1.0.4.dist-info/top_level.txt
codescribe-1.0.4.dist-info/RECORD
