Metadata-Version: 2.1
Name: codescribe
Version: 1.0.4
Summary: A package to convert GitHub repositories to formatted text.
Home-page: https://github.com/AashishNandakumar/codescribe
Author: Aashish Nandakumar
Author-email: aashishnkumar@gmail.com
Project-URL: issue_tracker, https://github.com/AashishNandakumar/codescribe/issues
Project-URL: repository, https://github.com/AashishNandakumar/codescribe
Classifier: Programming Language :: Python :: 3
Classifier: License :: OSI Approved :: MIT License
Classifier: Operating System :: OS Independent
Classifier: Intended Audience :: Developers
Classifier: Development Status :: 3 - Alpha
Requires-Python: >=3.6
